hz/__init__.py
hz-0.0.7.dist-info/licenses/LICENSE
hz-0.0.7.dist-info/METADATA
hz-0.0.7.dist-info/WHEEL
hz-0.0.7.dist-info/top_level.txt
hz-0.0.7.dist-info/RECORD
