Metadata-Version: 2.4
Name: hz
Version: 0.0.7
Summary: A collection of functions to generate synthetic data from real labeled data itself.
Home-page: https://github.com/t-c-w/hz
Author: Thor Whalen
License: apache-2.0
Platform: any
License-File: LICENSE
Dynamic: license-file
